langchain_contrib/__init__.py
langchain_contrib/chains/__init__.py
langchain_contrib/chains/choice.py
langchain_contrib/chains/mrkl/__init__.py
langchain_contrib/chains/mrkl/choice.py
langchain_contrib/chains/mrkl/pick_action.py
langchain_contrib/chains/mrkl/prompt.py
langchain_contrib/chains/testing.py
langchain_contrib/chains/tool.py
langchain_contrib/llms/__init__.py
langchain_contrib/llms/human/__init__.py
langchain_contrib/llms/human/llm.py
langchain_contrib/llms/human/patchers.py
langchain_contrib/llms/testing.py
langchain_contrib/prompts/__init__.py
langchain_contrib/prompts/chained.py
langchain_contrib/prompts/choice/__init__.py
langchain_contrib/prompts/choice/prompt_value.py
langchain_contrib/prompts/choice/template.py
langchain_contrib/prompts/prefixed.py
langchain_contrib/prompts/schema.py
langchain_contrib/tools/__init__.py
langchain_contrib/tools/terminal/__init__.py
langchain_contrib/tools/terminal/ansi_escapes.py
langchain_contrib/tools/terminal/patchers/__init__.py
langchain_contrib/tools/terminal/patchers/langchain_patch.py
langchain_contrib/tools/terminal/patchers/vcr_patch.py
langchain_contrib/tools/terminal/safety.py
langchain_contrib/tools/terminal/terminal.py
langchain_contrib/tools/terminal/tool.py
langchain_contrib/utils/__init__.py
langchain_contrib/utils/contexts.py
langchain_contrib/utils/fvalues.py
langchain_contrib/utils/llm.py
langchain_contrib/utils/safe.py
langchain_contrib-0.0.4.dist-info/METADATA
langchain_contrib-0.0.4.dist-info/WHEEL
langchain_contrib-0.0.4.dist-info/LICENSE
langchain_contrib-0.0.4.dist-info/RECORD
