Metadata-Version: 2.1
Name: langchain-contrib
Version: 0.0.4
Summary: 
Author: Amos Jun-yeung Ng
Author-email: me@amos.ng
Requires-Python: >=3.9,<4.0
Classifier: Programming Language :: Python :: 3
Classifier: Programming Language :: Python :: 3.9
Classifier: Programming Language :: Python :: 3.10
Classifier: Programming Language :: Python :: 3.11
Requires-Dist: fvalues (>=0.0.3,<0.0.4)
Requires-Dist: langchain (>=0.0.119,<0.0.120)
Requires-Dist: pexpect (>=4.8.0,<5.0.0)
Requires-Dist: simple-term-menu (>=1.6.1,<2.0.0)
